dispatcher/__init__.py
dispatcher/dispatcher.py
influxdispatcher-1.0.0.dist-info/METADATA
influxdispatcher-1.0.0.dist-info/WHEEL
influxdispatcher-1.0.0.dist-info/top_level.txt
influxdispatcher-1.0.0.dist-info/RECORD
