Metadata-Version: 2.1
Name: influxdispatcher
Version: 1.0.0
Summary: A simple asynchronous/non-asynchronous package for sending requests
Home-page: UNKNOWN
Author: Jake Strouse
Author-email: jstrouse@meh.llc
License: MIT
Platform: UNKNOWN
Classifier: License :: OSI Approved :: MIT License
Classifier: Programming Language :: Python :: 3
Classifier: Programming Language :: Python :: 3.8
Requires-Dist: loguru
Requires-Dist: requests
Requires-Dist: aiohttp
